pyenasolar/__init__.py
pyenasolar-1.0.0.dist-info/LICENSE
pyenasolar-1.0.0.dist-info/METADATA
pyenasolar-1.0.0.dist-info/WHEEL
pyenasolar-1.0.0.dist-info/top_level.txt
pyenasolar-1.0.0.dist-info/RECORD
