Metadata-Version: 2.1
Name: pyenasolar
Version: 1.0.0
Summary: Library to communicate with EnaSolar inverters
Home-page: https://github.com/geustace/pyenasolar
Author: geustace
Author-email: glen@eustace.nz
Classifier: Programming Language :: Python :: 3
Classifier: License :: OSI Approved :: Apache Software License
Classifier: Operating System :: OS Independent
Requires-Python: >=3.6
License-File: LICENSE
